{
  "version-3.0.0/someSidebar": [
    {
      "collapsed": true,
      "type": "category",
      "label": "Getting Started",
      "items": [
        {
          "type": "doc",
          "id": "version-3.0.0/gettingStarted/introduction"
        },
        {
          "type": "doc",
          "id": "version-3.0.0/gettingStarted/quick-start"
        },
        {
          "type": "doc",
          "id": "version-3.0.0/gettingStarted/setup"
        },
        {
          "type": "doc",
          "id": "version-3.0.0/gettingStarted/endpoints"
        },
        {
          "type": "doc",
          "id": "version-3.0.0/gettingStarted/api"
        },
        {
          "type": "doc",
          "id": "version-3.0.0/gettingStarted/samples"
        }
      ]
    },
    {
      "collapsed": true,
      "type": "category",
      "label": "Features",
      "items": [
        {
          "type": "doc",
          "id": "version-3.0.0/features/content-negotiation"
        },
        {
          "type": "doc",
          "id": "version-3.0.0/features/validation"
        },
        {
          "type": "doc",
          "id": "version-3.0.0/features/orchestration"
        },
        {
          "type": "doc",
          "id": "version-3.0.0/features/transformation"
        },
        {
          "type": "doc",
          "id": "version-3.0.0/features/mapping"
        },
        {
          "type": "doc",
          "id": "version-3.0.0/features/state-management"
        }
      ]
    }
  ]
}
